{
    "id": "Main Level",
    "name": "Stereo Madness",
    "author": "beefchip",
    "creators": ["beefchip"],
    "verifier": "sp0nplays",
    "verification": "https://www.youtube.com/watch?v=NIPLcqfWbwg",
    "percentToQualify": 100,
    "records": [
        {
            "user": "MagmaFilda",
            "link": "https://www.youtube.com/watch?v=07dcPy2wzls&t=512s",
            "percent": 100,
            "hz": 165
        },
        {
            "user": "xanyxgd",
            "link": "https://youtu.be/iThblvfz6XM",
            "percent": 100,
            "hz": 60
        },
        {
            "user": "Cyclestar",
            "link": "https://youtu.be/GVw71cSTKjI?si=m4EeZlk65NMosQDM",
            "percent": 100,
            "hz": 120
        },
        {
			"user": "SimonCTM",
			"link": "https://www.youtube.com/watch?v=NHMXC0w_ZVc",
			"percent": 100,
			"hz": 165
		}
    ]
}
